{
  "project_info": {
    "project_number": "128731869307",
    "project_id": "virtualstudyroom-cfc3a",
    "storage_bucket": "virtualstudyroom-cfc3a.firebasestorage.app"
  },
  "client": [
    {
      "client_info": {
        "mobilesdk_app_id": "1:128731869307:android:2665dc93504987f2af72de",
        "android_client_info": {
          "package_name": "com.example.demoflutter"
        }
      },
      "oauth_client": [],
      "api_key": [
        {
          "current_key": "AIzaSyDWZfWDf4W35eKPo-Y2j2Zedl9-KIwi7O8"
        }
      ],
      "services": {
        "appinvite_service": {
          "other_platform_oauth_client": []
        }
      }
    }
  ],
  "configuration_version": "1"
}